sbrunner_hooks/__init__.py
sbrunner_hooks/canonicalize.py
sbrunner_hooks/copyright.py
sbrunner_hooks/prospector_to_ruff.py
sbrunner_hooks/run_in_dir.py
sbrunner_hooks/workflow_timeout.py
sbrunner_hooks-1.6.1.dist-info/LICENSE
sbrunner_hooks-1.6.1.dist-info/METADATA
sbrunner_hooks-1.6.1.dist-info/WHEEL
sbrunner_hooks-1.6.1.dist-info/entry_points.txt
sbrunner_hooks-1.6.1.dist-info/RECORD
