Metadata-Version: 2.3
Name: sbrunner-hooks
Version: 1.6.1
Summary: Pre commit hook by sbrunner
License: BSD-2-Clause
Keywords: pre-commit
Author: Stéphane Brunner
Author-email: stephane.brunner@gmail.com
Requires-Python: >=3.9
Classifier: Development Status :: 5 - Production/Stable
Classifier: Environment :: Console
Classifier: License :: OSI Approved :: BSD License
Classifier: Operating System :: OS Independent
Classifier: Programming Language :: Python
Classifier: Programming Language :: Python :: 3
Classifier: Programming Language :: Python :: 3.9
Classifier: Programming Language :: Python :: 3.10
Classifier: Programming Language :: Python :: 3.11
Classifier: Programming Language :: Python :: 3.12
Classifier: Programming Language :: Python :: 3.13
Classifier: Typing :: Typed
Requires-Dist: PyYAML
Requires-Dist: multi-repo-automation
Requires-Dist: prospector
Requires-Dist: ruamel-yaml
Project-URL: Bug Tracker, https://github.com/sbrunner/hooks/issues
Project-URL: Repository, https://github.com/sbrunner/hooks
